pytest_nb/__init__.py
pytest_nb/cell.py
pytest_nb/kernel.py
pytest_nb/notebook.py
pytest_nb/test_notebook.py
pytest_nb/tester.py
pytest_nb-0.1.1.dist-info/licenses/LICENSE
pytest_nb-0.1.1.dist-info/METADATA
pytest_nb-0.1.1.dist-info/WHEEL
pytest_nb-0.1.1.dist-info/entry_points.txt
pytest_nb-0.1.1.dist-info/top_level.txt
pytest_nb-0.1.1.dist-info/RECORD
